CHANGELOG.rst
LICENSE
LICENSE_python-template-repo
MANIFEST.in
README.rst
install.py
pyproject.toml
requirements-dev.txt
requirements-docs.txt
requirements-test.txt
requirements.txt
setup.py
rc_repo_utils.egg-info/PKG-INFO
rc_repo_utils.egg-info/SOURCES.txt
rc_repo_utils.egg-info/dependency_links.txt
rc_repo_utils.egg-info/entry_points.txt
rc_repo_utils.egg-info/requires.txt
rc_repo_utils.egg-info/top_level.txt
repo_utils/__init__.py
repo_utils/__meta__.py
repo_utils/module.py
repo_utils/project/__init__.py
repo_utils/project/definitions/__init__.py
repo_utils/project/definitions/def_from_dir/__init__.py
repo_utils/project/definitions/def_from_dir/def_from_dir.py
repo_utils/project/definitions/def_from_dir/test_def_from_dir.py
repo_utils/project/definitions/define/__init__.py
repo_utils/project/definitions/define/define.py
repo_utils/project/definitions/define/test_define.py
repo_utils/project/definitions/find_definition/__init__.py
repo_utils/project/definitions/find_definition/find_definition.py
repo_utils/project/definitions/find_definition/test_find_definition.py
repo_utils/project/definitions/import_all_defs/__init__.py
repo_utils/project/definitions/import_all_defs/import_all_defs.py
repo_utils/project/definitions/import_all_defs/test_import_all_defs.py
repo_utils/project/definitions/import_definition/__init__.py
repo_utils/project/definitions/import_definition/import_definition.py
repo_utils/project/definitions/import_definition/test_import_definition.py
repo_utils/project/definitions/import_from_dir/__init__.py
repo_utils/project/definitions/import_from_dir/import_from_dir.py
repo_utils/project/definitions/import_from_dir/test_import_from_dir.py
repo_utils/project/definitions/import_from_path/__init__.py
repo_utils/project/definitions/import_from_path/import_from_path.py
repo_utils/project/definitions/import_from_path/test_import_from_path.py
repo_utils/project/definitions/rename_def/__init__.py
repo_utils/project/definitions/rename_def/rename_def.py
repo_utils/project/definitions/rename_def/test_rename_def.py
repo_utils/project/enable_installing_dependencies/__init__.py
repo_utils/project/enable_installing_dependencies/enable_installing_dependencies.py
