Metadata-Version: 2.1
Name: rc-repo-utils
Version: 0.2.1
Summary: Repository utilities to facilitate collaborative and modularized coding.
Home-page: 
Author: Joshua Mathias
Author-email: joshuaamathias@gmail.com
License: MIT
Classifier: Natural Language :: English
Classifier: Programming Language :: Python
Classifier: Programming Language :: Python :: 3
Classifier: Programming Language :: Python :: 3.6
Classifier: Programming Language :: Python :: 3.7
Classifier: Programming Language :: Python :: 3.8
Classifier: Programming Language :: Python :: 3.9
Requires-Python: >=3.6
Provides-Extra: dev
Provides-Extra: docs
Provides-Extra: test
Provides-Extra: all
License-File: LICENSE
License-File: LICENSE_python-template-repo
